[
  {
    "title": "Let's Dance 11",
    "theme": "Pokémon",
    "year": "1999",
    "image": "images/lets-dance-11.jpg"
  },
  {
    "title": "Let's Dance 12",
    "theme": "Pokémon",
    "year": "1999",
     "image": "images/lets-dance-12.jpg"
  },
  {
    "title": "Jirachi Wish Maker Movie Promotion",
    "theme": "Pokémon",
    "year": "2003",
    "image": "images/jirachi-wish-maker-movie-promotion-1.jpg"
  },
   {
    "title": "Jirachi Wish Maker Movie Promotion",
    "theme": "Pokémon",
    "year": "2003",
    "image": "images/jirachi-wish-maker-movie-promotion-2.jpg"
  },
]
